[{"type": "Car", "occluded_state": 0, "truncated_state": 0, "alpha": -1.461678160745448, "2d_box": {"xmin": 1308.115479, "ymin": 564.996765, "xmax": 1348.188965, "ymax": 594.3572389999999}, "3d_dimensions": {"h": 1.407225, "w": 1.406522, "l": 4.245831}, "3d_location": {"x": 41.17476, "y": -14.86134, "z": -0.5903046}, "rotation": -0.4533234}, {"type": "Car", "occluded_state": 0, "truncated_state": 0, "alpha": 2.7407990191582603, "2d_box": {"xmin": 98.645546, "ymin": 572.562988, "xmax": 382.664528, "ymax": 649.412109}, "3d_dimensions": {"h": 1.46306, "w": 2.107235, "l": 4.044728}, "3d_location": {"x": 16.48997, "y": 17.24065, "z": -1.101755}, "rotation": 2.774146}, {"type": "Car", "occluded_state": 0, "truncated_state": 0, "alpha": -0.9807524939224387, "2d_box": {"xmin": 813.639282, "ymin": 573.400635, "xmax": 1016.263611, "ymax": 655.7195439999999}, "3d_dimensions": {"h": 1.334601, "w": 1.26126, "l": 5.076152}, "3d_location": {"x": 15.25568, "y": 2.09366, "z": -0.9818845}, "rotation": -0.4533234}, {"type": "Tricyclist", "occluded_state": 1, "truncated_state": 0, "alpha": 2.4241341085585866, "2d_box": {"xmin": 610.212646, "ymin": 569.693542, "xmax": 644.455871, "ymax": 592.7275999999999}, "3d_dimensions": {"h": 1.402834, "w": 1.362419, "l": 1.382592}, "3d_location": {"x": 48.24884, "y": 25.44253, "z": -0.9675127}, "rotation": 2.772398}, {"type": "Car", "occluded_state": 1, "truncated_state": 0, "alpha": 2.6733636571931845, "2d_box": {"xmin": 377.470428, "ymin": 560.53363, "xmax": 446.17453, "ymax": 586.036071}, "3d_dimensions": {"h": 1.71367, "w": 1.828351, "l": 3.405252}, "3d_location": {"x": 53.20869, "y": 43.45059, "z": -0.5723448}, "rotation": 2.722438}, {"type": "Car", "occluded_state": 2, "truncated_state": 0, "alpha": 2.342163419972825, "2d_box": {"xmin": 758.648743, "ymin": 560.905884, "xmax": 798.497986, "ymax": 574.648682}, "3d_dimensions": {"h": 1.454463, "w": 1.868503, "l": 4.087948}, "3d_location": {"x": 85.29641, "y": 27.98788, "z": 0.012544}, "rotation": 2.68698}, {"type": "Bus", "occluded_state": 1, "truncated_state": 2, "alpha": 2.8725897949115393, "2d_box": {"xmin": 0, "ymin": 464.957336, "xmax": 387.958252, "ymax": 663.774902}, "3d_dimensions": {"h": 3.576522, "w": 3.073819, "l": 10.702592}, "3d_location": {"x": 18.46631, "y": 22.98393, "z": -0.245045}, "rotation": 2.729134}, {"type": "Car", "occluded_state": 1, "truncated_state": 0, "alpha": 2.443230213959218, "2d_box": {"xmin": 665.516113, "ymin": 561.353027, "xmax": 713.074829, "ymax": 576.106994}, "3d_dimensions": {"h": 1.368979, "w": 1.836917, "l": 4.011591}, "3d_location": {"x": 74.52917, "y": 33.13779, "z": -0.1483299}, "rotation": 2.68698}, {"type": "Car", "occluded_state": 2, "truncated_state": 0, "alpha": 2.3260131930171255, "2d_box": {"xmin": 801.673157, "ymin": 559.201965, "xmax": 837.6957399999999, "ymax": 573.978882}, "3d_dimensions": {"h": 1.660836, "w": 1.894666, "l": 3.909432}, "3d_location": {"x": 90.63972, "y": 24.92707, "z": 0.1843731}, "rotation": 2.654559}, {"type": "Car", "occluded_state": 0, "truncated_state": 0, "alpha": 2.1362430273653863, "2d_box": {"xmin": 876.302856, "ymin": 565.46344, "xmax": 934.674804, "ymax": 590.648377}, "3d_dimensions": {"h": 1.686006, "w": 2.0692, "l": 4.324363}, "3d_location": {"x": 55.35459, "y": 9.093286, "z": -0.7407318}, "rotation": 2.738989}, {"type": "Car", "occluded_state": 1, "truncated_state": 0, "alpha": 2.5315151533448845, "2d_box": {"xmin": 541.290588, "ymin": 559.394104, "xmax": 598.4984129999999, "ymax": 577.750488}, "3d_dimensions": {"h": 1.469568, "w": 1.83911, "l": 3.818999}, "3d_location": {"x": 63.96556, "y": 38.55785, "z": -0.1955388}, "rotation": 2.722438}, {"type": "Motorcyclist", "occluded_state": 0, "truncated_state": 0, "alpha": 4.681574642662845, "2d_box": {"xmin": 1433.636353, "ymin": 562.857605, "xmax": 1449.9925540000002, "ymax": 597.790527}, "3d_dimensions": {"h": 1.568424, "w": 0.583372, "l": 1.856711}, "3d_location": {"x": 37.71424, "y": -18.71974, "z": -0.5770643}, "rotation": -0.4271784}, {"type": "Car", "occluded_state": 1, "truncated_state": 0, "alpha": 2.60077073867308, "2d_box": {"xmin": 461.661682, "ymin": 560.834839, "xmax": 530.436828, "ymax": 581.081177}, "3d_dimensions": {"h": 1.484515, "w": 1.841887, "l": 4.079607}, "3d_location": {"x": 58.54855, "y": 41.09035, "z": -0.4022208}, "rotation": 2.722438}, {"type": "Car", "occluded_state": 1, "truncated_state": 0, "alpha": 2.267580760105817, "2d_box": {"xmin": 748.893066, "ymin": 563.796204, "xmax": 833.945556, "ymax": 600.745179}, "3d_dimensions": {"h": 1.611973, "w": 1.365084, "l": 4.338238}, "3d_location": {"x": 36.37645, "y": 11.27299, "z": -0.7837683}, "rotation": 2.744623}, {"type": "Van", "occluded_state": 0, "truncated_state": 0, "alpha": -1.3647885145006096, "2d_box": {"xmin": 1212.489136, "ymin": 554.45575, "xmax": 1244.601197, "ymax": 582.7636719999999}, "3d_dimensions": {"h": 1.884986, "w": 1.162633, "l": 4.856128}, "3d_location": {"x": 56.27177, "y": -13.44803, "z": -0.01155801}, "rotation": -0.4393352}, {"type": "Trafficcone", "occluded_state": 0, "truncated_state": 0, "alpha": 0, "2d_box": {"xmin": 1387.7859623092, "ymin": 629.5809020869, "xmax": 1407.2102824135, "ymax": 671.4850533232}, "3d_dimensions": {"h": 0, "w": 0, "l": 0}, "3d_location": {"x": 0.0, "y": 0.0, "z": 0.0}, "rotation": 0.0}, {"type": "Car", "occluded_state": 1, "truncated_state": 0, "alpha": 0, "2d_box": {"xmin": 1080.7726109139, "ymin": 561.3485421454, "xmax": 1108.9801779956001, "ymax": 575.4523256862}, "3d_dimensions": {"h": 0, "w": 0, "l": 0}, "3d_location": {"x": 0.0, "y": 0.0, "z": 0.0}, "rotation": 0.0}, {"type": "Car", "occluded_state": 2, "truncated_state": 0, "alpha": 0, "2d_box": {"xmin": 610.0347701679, "ymin": 561.2544342462, "xmax": 663.6880888081, "ymax": 578.6841846519001}, "3d_dimensions": {"h": 0, "w": 0, "l": 0}, "3d_location": {"x": 0.0, "y": 0.0, "z": 0.0}, "rotation": 0.0}]