[{"type": "Car", "occluded_state": 0, "truncated_state": 2, "alpha": -1.093311098567106, "2d_box": {"xmin": 1716.015381, "ymin": 564.380615, "xmax": 1919.0, "ymax": 644.409485}, "3d_dimensions": {"h": 1.416709, "w": 1.880871, "l": 4.496665}, "3d_location": {"x": 16.34259, "y": -16.04915, "z": -0.7849433}, "rotation": -1.246815}, {"type": "Car", "occluded_state": 2, "truncated_state": 0, "alpha": 2.871478831382061, "2d_box": {"xmin": 924.223755, "ymin": 562.480652, "xmax": 1027.761719, "ymax": 602.00708}, "3d_dimensions": {"h": 1.720704, "w": 1.94792, "l": 4.349462}, "3d_location": {"x": 36.06887, "y": 2.744481, "z": -0.7506129}, "rotation": 1.917287}, {"type": "Trafficcone", "occluded_state": 0, "truncated_state": 0, "alpha": -0.24356715974558335, "2d_box": {"xmin": 974.96991, "ymin": 590.071167, "xmax": 981.68512, "ymax": 611.983582}, "3d_dimensions": {"h": 0.666918, "w": 0.389359, "l": 0.116106}, "3d_location": {"x": 24.60773, "y": 1.780011, "z": -1.187615}, "rotation": -1.254361}, {"type": "Van", "occluded_state": 1, "truncated_state": 0, "alpha": 2.8194188669250515, "2d_box": {"xmin": 957.333008, "ymin": 553.788635, "xmax": 1069.20166, "ymax": 602.76239}, "3d_dimensions": {"h": 1.946729, "w": 1.946691, "l": 4.267886}, "3d_location": {"x": 33.13977, "y": 0.9626461, "z": -0.5446736}, "rotation": 1.922753}, {"type": "Car", "occluded_state": 2, "truncated_state": 0, "alpha": 2.441174558617982, "2d_box": {"xmin": 1333.582153, "ymin": 555.002258, "xmax": 1379.5576170000002, "ymax": 568.8644409999999}, "3d_dimensions": {"h": 1.368347, "w": 1.850672, "l": 4.032076}, "3d_location": {"x": 83.45692, "y": -32.77904, "z": 0.8527251}, "rotation": 1.897847}, {"type": "Bus", "occluded_state": 1, "truncated_state": 0, "alpha": 2.243213657885722, "2d_box": {"xmin": 1473.415283, "ymin": 522.666077, "xmax": 1630.6335450000001, "ymax": 581.403138}, "3d_dimensions": {"h": 3.226965, "w": 2.965116, "l": 8.302505}, "3d_location": {"x": 48.12981, "y": -30.08714, "z": 0.9294207}, "rotation": 1.912583}, {"type": "Car", "occluded_state": 0, "truncated_state": 0, "alpha": 4.582395557549482, "2d_box": {"xmin": 736.951416, "ymin": 564.692993, "xmax": 749.453003, "ymax": 574.461975}, "3d_dimensions": {"h": 1.44114, "w": 1.256074, "l": 4.276012}, "3d_location": {"x": 118.0055, "y": 44.19302, "z": -0.1613874}, "rotation": 0.4879902}, {"type": "Car", "occluded_state": 0, "truncated_state": 0, "alpha": 2.050810512173829, "2d_box": {"xmin": 1894.955566, "ymin": 547.931519, "xmax": 1919.0, "ymax": 565.8023079999999}, "3d_dimensions": {"h": 1.090348, "w": 1.871483, "l": 4.293351}, "3d_location": {"x": 54.8335, "y": -58.4967, "z": 0.9296424}, "rotation": 1.845561}, {"type": "Car", "occluded_state": 1, "truncated_state": 0, "alpha": 2.4428701639761377, "2d_box": {"xmin": 1321.44519, "ymin": 560.288147, "xmax": 1415.6175529999998, "ymax": 589.487305}, "3d_dimensions": {"h": 1.361582, "w": 1.852106, "l": 3.82263}, "3d_location": {"x": 39.39536, "y": -16.07861, "z": -0.3565951}, "rotation": 1.884296}, {"type": "Tricyclist", "occluded_state": 0, "truncated_state": 0, "alpha": 2.372338434319948, "2d_box": {"xmin": 1431.046875, "ymin": 560.410095, "xmax": 1469.667236, "ymax": 578.4161369999999}, "3d_dimensions": {"h": 1.386338, "w": 1.52603, "l": 2.171996}, "3d_location": {"x": 64.42126, "y": -32.54288, "z": 0.04356407}, "rotation": 1.873722}, {"type": "Van", "occluded_state": 0, "truncated_state": 0, "alpha": 3.587131759935793, "2d_box": {"xmin": 262.146637, "ymin": 560.94696, "xmax": 427.148346, "ymax": 615.527099}, "3d_dimensions": {"h": 1.99865, "w": 1.853019, "l": 4.561387}, "3d_location": {"x": 29.1279, "y": 26.41194, "z": -1.001964}, "rotation": 1.858946}, {"type": "Car", "occluded_state": 1, "truncated_state": 0, "alpha": 2.6397432396919354, "2d_box": {"xmin": 1232.500854, "ymin": 553.957764, "xmax": 1277.8488759999998, "ymax": 569.94043}, "3d_dimensions": {"h": 1.52784, "w": 1.889261, "l": 3.797959}, "3d_location": {"x": 79.79394, "y": -21.55707, "z": 0.7643486}, "rotation": 1.809552}, {"type": "Car", "occluded_state": 0, "truncated_state": 0, "alpha": 2.6359764407722626, "2d_box": {"xmin": 1066.637085, "ymin": 565.152954, "xmax": 1180.469116, "ymax": 603.754639}, "3d_dimensions": {"h": 1.45218, "w": 1.860394, "l": 4.052077}, "3d_location": {"x": 31.66759, "y": -3.463354, "z": -0.7423151}, "rotation": 1.969092}, {"type": "Car", "occluded_state": 1, "truncated_state": 0, "alpha": 2.4520572354337618, "2d_box": {"xmin": 1423.007446, "ymin": 553.753052, "xmax": 1463.6041260000002, "ymax": 567.5220340000001}, "3d_dimensions": {"h": 1.412273, "w": 1.820216, "l": 3.342803}, "3d_location": {"x": 86.90551, "y": -43.12156, "z": 1.072654}, "rotation": 1.800651}, {"type": "Car", "occluded_state": 2, "truncated_state": 0, "alpha": 2.4340845975143655, "2d_box": {"xmin": 1307.539429, "ymin": 559.928467, "xmax": 1383.55188, "ymax": 587.0040899999999}, "3d_dimensions": {"h": 1.634856, "w": 1.82745, "l": 4.123015}, "3d_location": {"x": 50.65864, "y": -19.26305, "z": -0.3025265}, "rotation": 1.916657}, {"type": "Van", "occluded_state": 1, "truncated_state": 0, "alpha": -1.0758949250002618, "2d_box": {"xmin": 1719.813232, "ymin": 545.559937, "xmax": 1862.8061519999999, "ymax": 605.8424689999999}, "3d_dimensions": {"h": 1.664992, "w": 1.998087, "l": 2.497504}, "3d_location": {"x": 24.42966, "y": -22.08414, "z": -0.2870183}, "rotation": -1.225361}, {"type": "Van", "occluded_state": 1, "truncated_state": 0, "alpha": 2.728878769591896, "2d_box": {"xmin": 1073.877075, "ymin": 554.630005, "xmax": 1125.3674310000001, "ymax": 575.216431}, "3d_dimensions": {"h": 1.857122, "w": 1.841887, "l": 4.358741}, "3d_location": {"x": 74.35568, "y": -5.875876, "z": 0.3629915}, "rotation": 1.905157}, {"type": "Car", "occluded_state": 1, "truncated_state": 0, "alpha": 2.699351316693771, "2d_box": {"xmin": 1117.623535, "ymin": 561.228699, "xmax": 1201.9083249999999, "ymax": 593.6336670000001}, "3d_dimensions": {"h": 1.666397, "w": 1.873358, "l": 3.96279}, "3d_location": {"x": 42.70732, "y": -6.563099, "z": -0.5457129}, "rotation": 1.861897}, {"type": "Cyclist", "occluded_state": 0, "truncated_state": 1, "alpha": 0.9806871886167093, "2d_box": {"xmin": 0, "ymin": 666.283203, "xmax": 136.265594, "ymax": 1049.70227}, "3d_dimensions": {"h": 1.309205, "w": 0.695374, "l": 1.641882}, "3d_location": {"x": 2.816362, "y": 4.847806, "z": -1.375797}, "rotation": -1.535258}, {"type": "Van", "occluded_state": 0, "truncated_state": 0, "alpha": -0.15588351980288723, "2d_box": {"xmin": 870.445313, "ymin": 555.266724, "xmax": 906.065247, "ymax": 573.452271}, "3d_dimensions": {"h": 2.012082, "w": 1.858278, "l": 3.758119}, "3d_location": {"x": 89.5211, "y": 16.7728, "z": 0.4641792}, "rotation": -1.229804}, {"type": "Car", "occluded_state": 2, "truncated_state": 0, "alpha": 2.6537329618025374, "2d_box": {"xmin": 1127.58667, "ymin": 556.44104, "xmax": 1171.7861329999998, "ymax": 572.676331}, "3d_dimensions": {"h": 1.492869, "w": 1.905109, "l": 3.633979}, "3d_location": {"x": 76.14181, "y": -10.73579, "z": 0.4335805}, "rotation": 1.91919}, {"type": "Car", "occluded_state": 1, "truncated_state": 0, "alpha": 2.5796163750894867, "2d_box": {"xmin": 1175.568604, "ymin": 555.490234, "xmax": 1226.2822270000001, "ymax": 575.0062859999999}, "3d_dimensions": {"h": 1.833277, "w": 1.896922, "l": 4.402323}, "3d_location": {"x": 77.97805, "y": -15.91209, "z": 0.4016124}, "rotation": 1.932216}, {"type": "Car", "occluded_state": 1, "truncated_state": 0, "alpha": 0, "2d_box": {"xmin": 1823.1147736085, "ymin": 547.1738505387, "xmax": 1891.1362691048998, "ymax": 576.6377068767}, "3d_dimensions": {"h": 0, "w": 0, "l": 0}, "3d_location": {"x": 0.0, "y": 0.0, "z": 0.0}, "rotation": 0.0}, {"type": "Car", "occluded_state": 1, "truncated_state": 0, "alpha": 0, "2d_box": {"xmin": 1285.3813807825, "ymin": 556.0844692964, "xmax": 1331.3049840254, "ymax": 571.240773997}, "3d_dimensions": {"h": 0, "w": 0, "l": 0}, "3d_location": {"x": 0.0, "y": 0.0, "z": 0.0}, "rotation": 0.0}]